[
  {
    "title": "Connection Settings",
    "fields": [
      {
        "type": "textInput",
        "label": "Trackity Endpoint",
        "value": "endpoint",
        "required": true,
        "placeholder": "e.g: https://trackity.tiki.vn/tracking"
      },
      {
        "type": "textInput",
        "label": "Access Key",
        "value": "accessKey",
        "regex": "^(.{0,100})$",
        "regexErrorMessage": "Invalid Access Key",
        "required": true,
        "placeholder": "e.g: 1111c112a1b2531170f676e052cffpro",
        "secret": true
      }
    ]
  }
]